wx_icons_hicolor
