Metadata-Version: 2.1
Name: wx-icons-hicolor
Version: 0.2.0
Summary: Hicolor icon theme for wxPython.
Home-page: https://github.com/domdfcoding/custom_wx_icons_hicolor
Author: Dominic Davis-Foster
Author-email: dominic@davis-foster.co.uk
License: GNU Lesser General Public License v3 or later (LGPLv3+)
Project-URL: Documentation, https://custom_wx_icons_hicolor.readthedocs.io
Project-URL: Issue_Tracker, https://github.com/domdfcoding/custom_wx_icons_hicolor/issues
Project-URL: Source_Code, https://github.com/domdfcoding/custom_wx_icons_hicolor
Keywords: wxPython,icons,iconset
Platform: Windows
Platform: macOS
Platform: Linux
Classifier: Development Status :: 3 - Alpha
Classifier: Environment :: X11 Applications :: GTK
Classifier: Intended Audience :: Developers
Classifier: License :: OSI Approved :: GNU Lesser General Public License v3 or later (LGPLv3+)
Classifier: Operating System :: OS Independent
Classifier: Programming Language :: Python
Classifier: Programming Language :: Python :: 3 :: Only
Classifier: Programming Language :: Python :: 3.6
Classifier: Programming Language :: Python :: 3.7
Classifier: Programming Language :: Python :: 3.8
Classifier: Programming Language :: Python :: 3.9
Classifier: Programming Language :: Python :: Implementation :: CPython
Classifier: Topic :: Desktop Environment :: Gnome
Classifier: Topic :: Software Development :: Libraries :: Python Modules
Classifier: Topic :: Software Development :: User Interfaces
Classifier: Typing :: Typed
Requires-Python: >=3.6.1
Requires-Dist: cairosvg (>=2.4.2)
Requires-Dist: consolekit (>=0.6.0)
Requires-Dist: domdf-python-tools (>=1.7.0)
Requires-Dist: memoized-property (>=1.0.3)
Requires-Dist: python-magic (>=0.4.15)
Requires-Dist: typing-extensions (>=3.7.4.3)
Requires-Dist: wxpython (>=4.0.7) ; platform_system == "Darwin" and python_version < "3.9"
Requires-Dist: wxpython (>=4.0.7) ; platform_system == "Windows" and python_version < "3.9"
Provides-Extra: all
